zero_shot_labeler/__init__.py
zero_shot_labeler/lambda_handler.py
zero_shot_labeler-0.1.3.dist-info/LICENSE
zero_shot_labeler-0.1.3.dist-info/METADATA
zero_shot_labeler-0.1.3.dist-info/WHEEL
zero_shot_labeler-0.1.3.dist-info/RECORD
