Metadata-Version: 2.1
Name: zero_shot_labeler
Version: 0.1.3
Summary: A lightweight zero-shot labeler for text classification
Home-page: https://github.com/0xjgv/zero-shot-labeler
License: MIT
Author: Juan Gaitán-Villamizar
Author-email: juans.gaitan@gmail.com
Requires-Python: >=3.11
Classifier: License :: OSI Approved :: MIT License
Classifier: Programming Language :: Python :: 3
Classifier: Programming Language :: Python :: 3.11
Classifier: Programming Language :: Python :: 3.12
Classifier: Programming Language :: Python :: 3.13
Requires-Dist: transformers[torch] (>=4.46.3,<5.0.0)
Project-URL: Repository, https://github.com/0xjgv/zero-shot-labeler
